taskiq_aiopg/__init__.py
taskiq_aiopg/exceptions.py
taskiq_aiopg/py.typed
taskiq_aiopg/queries.py
taskiq_aiopg/result_backend.py
taskiq_aiopg-0.2.0.dist-info/licenses/LICENSE
taskiq_aiopg-0.2.0.dist-info/METADATA
taskiq_aiopg-0.2.0.dist-info/WHEEL
taskiq_aiopg-0.2.0.dist-info/top_level.txt
taskiq_aiopg-0.2.0.dist-info/RECORD
