Metadata-Version: 2.4
Name: taskiq-aiopg
Version: 0.2.0
Summary: Aiopg and PostgreSQL integration for taskiq
Author-email: Anfimov Dima <lovesolaristics@gmail.com>
Project-URL: Bug Tracker, https://github.com/danfimov/taskiq-aiopg/issues
Project-URL: Repository, https://github.com/danfimov/taskiq-aiopg/
Keywords: taskiq,tasks,distributed,async,aiopg
Classifier: Development Status :: 5 - Production/Stable
Classifier: Intended Audience :: Developers
Classifier: Intended Audience :: Information Technology
Classifier: Framework :: AsyncIO
Classifier: License :: OSI Approved :: MIT License
Classifier: Programming Language :: Python
Classifier: Programming Language :: Python :: 3
Classifier: Programming Language :: Python :: 3 :: Only
Classifier: Programming Language :: Python :: 3.9
Classifier: Programming Language :: Python :: 3.10
Classifier: Programming Language :: Python :: 3.11
Classifier: Programming Language :: Python :: 3.12
Classifier: Programming Language :: Python :: 3.13
Classifier: Programming Language :: Python :: Implementation :: CPython
Classifier: Topic :: Software Development :: Libraries :: Python Modules
Classifier: Topic :: Software Development :: Libraries
Classifier: Topic :: Software Development
Classifier: Topic :: System :: Networking
Classifier: Typing :: Typed
Classifier: Operating System :: OS Independent
Requires-Python: >=3.9
License-File: LICENSE
Requires-Dist: aiopg>=1.4.0
Requires-Dist: taskiq>=0.11.16
Dynamic: license-file
